memory_mcp.py
memory_tools.py
iflow_mcp_memory-0.1.1.dist-info/METADATA
iflow_mcp_memory-0.1.1.dist-info/WHEEL
iflow_mcp_memory-0.1.1.dist-info/entry_points.txt
iflow_mcp_memory-0.1.1.dist-info/top_level.txt
iflow_mcp_memory-0.1.1.dist-info/RECORD
