Metadata-Version: 2.4
Name: iflow-mcp-memory
Version: 0.1.1
Summary: A knowledge-graph-based memory system for AI agents that enables persistent information storage between conversations
Requires-Python: >=3.12
Requires-Dist: fastmcp>=2.3.3
Requires-Dist: ipykernel>=6.29.5
Requires-Dist: ipywidgets>=8.1.7
Requires-Dist: loguru>=0.7.3
Requires-Dist: pydantic-ai>=0.1.11
Requires-Dist: python-dotenv>=1.1.0
